LICENSE
README.md
pyproject.toml
setup.py
aliyun_sms_code/__init__.py
aliyun_sms_code/aliyun_sms_code.py
aliyun_sms_code.egg-info/PKG-INFO
aliyun_sms_code.egg-info/SOURCES.txt
aliyun_sms_code.egg-info/dependency_links.txt
aliyun_sms_code.egg-info/requires.txt
aliyun_sms_code.egg-info/top_level.txt