Metadata-Version: 2.1
Name: aliyun-sms-code
Version: 0.0.2
Summary: Sending verification codes through Aliyun SMS service.
Author: chentianbo
Author-email: chentianbo@xmov.ai
License-File: LICENSE
